laniakea_utils/__init__.py
laniakea_utils/api/__init__.py
laniakea_utils/api/api.py
laniakea_utils/api/app.py
laniakea_utils/api/galaxyctl.py
laniakea_utils/api/info.py
laniakea_utils/api/os_users_manager.py
laniakea_utils/common/__init__.py
laniakea_utils/common/log_facility.py
laniakea_utils/common/passphrase_generator.py
laniakea_utils/common/read_config.py
laniakea_utils/common/vault.py
laniakea_utils-0.2.0b3.dist-info/LICENSE.rst
laniakea_utils-0.2.0b3.dist-info/METADATA
laniakea_utils-0.2.0b3.dist-info/WHEEL
laniakea_utils-0.2.0b3.dist-info/top_level.txt
laniakea_utils-0.2.0b3.dist-info/RECORD
