Metadata-Version: 2.1
Name: laniakea-utils
Version: 0.2.0b3
Summary: Utilities for Laniakea applications
Author-email: Marco Antonio Tangaro <ma.tangaro@ibiom.cnr.it>
Project-URL: Homepage, https://github.com/Laniakea-elixir-it/laniakea-utils
Project-URL: Issues, https://github.com/Laniakea-elixir-it/laniakea-utils/issues
Classifier: Programming Language :: Python :: 3
Classifier: License :: OSI Approved :: GNU General Public License v3 (GPLv3)
Classifier: Operating System :: POSIX :: Linux
Requires-Python: >=3.6
License-File: LICENSE.rst
Requires-Dist: flask ==2.0.2
Requires-Dist: flaat ==1.1.18
Requires-Dist: gunicorn ==20.1.0
Requires-Dist: hvac ==0.11.2
Requires-Dist: Werkzeug ==2.0.2
